<?xml version="1.0" encoding="UTF-8"?>
<files psalm-version="4.x-dev@">
  <file src="src/Controller/Component/LoginRecorderComponent.php">
    <TypeDoesNotContainType occurrences="2">
      <code>empty($this-&gt;User)</code>
      <code>empty($this-&gt;Users)</code>
    </TypeDoesNotContainType>
  </file>
  <file src="src/Controller/Traits/GetStartAndEndDateTrait.php">
    <RedundantCast occurrences="2">
      <code>(int)($day ?: 1)</code>
      <code>(int)($month ?: 1)</code>
    </RedundantCast>
    <RedundantCondition occurrences="2">
      <code>1</code>
      <code>1</code>
    </RedundantCondition>
  </file>
  <file src="src/Model/Table/PostsTable.php">
    <TooManyTemplateParams occurrences="1">
      <code>\Cake\Collection\CollectionInterface&lt;\MeCms\Model\Entity\Post&gt;</code>
    </TooManyTemplateParams>
  </file>
  <file src="src/Model/Table/Traits/GetPreviewsFromTextTrait.php">
    <TooManyTemplateParams occurrences="1">
      <code>\Cake\Collection\CollectionInterface&lt;array{url: string, width: int, height: int}&gt;</code>
    </TooManyTemplateParams>
  </file>
  <file src="src/Policy/ControllerResolver.php">
    <MoreSpecificImplementedParamType occurrences="1">
      <code>$resource</code>
    </MoreSpecificImplementedParamType>
  </file>
  <file src="src/TestSuite/TestCase.php">
    <InternalMethod occurrences="1">
      <code>parent::__construct($name, $data, $dataName)</code>
    </InternalMethod>
  </file>
  <file src="templates/Admin/Pages/form.php">
    <TooManyTemplateParams occurrences="1">
      <code>$this-&gt;extend('MeCms./common/form');</code>
    </TooManyTemplateParams>
  </file>
  <file src="templates/Admin/Posts/form.php">
    <TooManyTemplateParams occurrences="1">
      <code>$this-&gt;extend('MeCms./common/form');</code>
    </TooManyTemplateParams>
  </file>
  <file src="templates/Posts/view.php">
    <TooManyTemplateParams occurrences="1">
      <code>$this-&gt;extend('/common/view');</code>
    </TooManyTemplateParams>
  </file>
  <file src="templates/cell/PostsTagsWidgets/popular_as_cloud.php">
    <TooManyTemplateParams occurrences="1"/>
  </file>
  <file src="templates/cell/PostsWidgets/months_as_form.php">
    <TooManyTemplateParams occurrences="1"/>
  </file>
  <file src="templates/cell/PostsWidgets/months_as_list.php">
    <TooManyTemplateParams occurrences="1"/>
  </file>
  <file src="tests/TestCase/Command/UsersCommandTest.php">
    <UndefinedPropertyAssignment occurrences="1">
      <code>$this-&gt;Command-&gt;Users</code>
    </UndefinedPropertyAssignment>
  </file>
  <file src="tests/TestCase/Form/ContactUsFormTest.php">
    <TypeDoesNotContainType occurrences="1">
      <code>empty($this-&gt;Form)</code>
    </TypeDoesNotContainType>
  </file>
  <file src="tests/TestCase/Policy/ControllerResolverTest.php">
    <InvalidArgument occurrences="1">
      <code>new \stdClass()</code>
    </InvalidArgument>
  </file>
  <file src="tests/TestCase/View/View/Admin/AppViewTest.php">
    <TypeDoesNotContainType occurrences="1">
      <code>empty($this-&gt;View)</code>
    </TypeDoesNotContainType>
  </file>
  <file src="tests/TestCase/View/View/AppViewTest.php">
    <TypeDoesNotContainType occurrences="1">
      <code>empty($this-&gt;View)</code>
    </TypeDoesNotContainType>
  </file>
  <file src="tests/TestCase/View/ViewTest.php">
    <TypeDoesNotContainType occurrences="1">
      <code>empty($this-&gt;View)</code>
    </TypeDoesNotContainType>
  </file>
</files>
